# chapter 2 Sequences - A 
- Contents
    - [Overview of python built-in Sequences](#1-overview-of-python-built-in-sequences)
    - [List comprehension & Generator expression](#2-list-comprehension--generator-expression)
    - [Tuple as a record or immutable list](#3-tuple-as-a-record-or-immutable-list)
    - [Sequence unpacking & pattern matching](#4-sequence-unpacking--pattern-matching)
    - [Slicing](#5-slicing)

## 1. Overview of python built-in Sequences

### Container VS Flat 
- Container Sequence
    - ì„œë¡œ ë‹¤ë¥¸ ìë£Œí˜•ì„ ë‹´ì„ ìˆ˜ ìˆëŠ” ì‹œí€€ìŠ¤
    - list / tuple / collections.deque 
    - ê°ì²´ì— ëŒ€í•œ ì°¸ì¡°ë¥¼ ë‹´ëŠ”ë‹¤! -> ê°œë³„ ìš”ì†ŒëŠ” ë³„ë„ íŒŒì´ì¬ ê°ì²´ì´ë‹¤!
- Flat Sequence
    - í•˜ë‚˜ì˜ ìë£Œí˜•ë§Œ ë‹´ì„ ìˆ˜ ìˆëŠ” ì‹œí€€ìŠ¤
    - str / bytes / array.array
    - ê°ì²´ì— ëŒ€í•œ ì°¸ì¡°ê°€ ì•„ë‹Œ, ê·¸ ê°’ì„ ì§ì ‘ ë‹´ëŠ”ë‹¤! (ì‹¤ìˆ˜ array ê°€ ì‹¤ìˆ˜ tuple ë³´ë‹¤ ë©”ëª¨ë¦¬ ëœ ë¨¹ëŠ” ì´ìœ  - **ë©”íƒ€ë°ì´í„° í•„ë“œ**ë¥¼ ì•ˆ ë‹´ìœ¼ë‹ˆê¹Œ!)

### Mutable VS Immutable
- Mutable Sequence
    - ê°€ë³€ ì‹œí€€ìŠ¤ list / bytearray / array.array / collections.deque 
- Immutable Sequence 
    - ë¶ˆë³€ ì‹œí€€ìŠ¤ tuple / str / bytes 
- ê°€ë³€ì‹œí€€ìŠ¤ê°€ ë¶ˆë³€ì‹œí€€ìŠ¤ë¥¼ ìƒì†í•˜ë©°, ì—¬ëŸ¬ ë©”ì„œë“œë¥¼ ì¶”ê°€ êµ¬í˜„í•¨
    - Sequence: ì½ê¸° ì „ìš© ì‹œí€€ìŠ¤ë¥¼ ìœ„í•œ ë©”ì„œë“œ ì •ì˜ (ex. \_\_getitem\_\_, \__\len\_\_)
	- MutableSequence: ì—¬ê¸°ì— ë”í•´ \_\_setitem\_\_, append(), remove() ê°™ì€ ì“°ê¸°/ìˆ˜ì • ê´€ë ¨ ë©”ì„œë“œë„ ìš”êµ¬ 
        ```python
        class MutableSequence(Sequence):
            __slots__ = ()

            """All the operations on a read-write sequence.

            Concrete subclasses must provide __new__ or __init__,
            __getitem__, __setitem__, __delitem__, __len__, and insert().

            """

            @abstractmethod
            def __setitem__(self, index, value):
                raise IndexError

            @abstractmethod
            def __delitem__(self, index):
                raise IndexError

            @abstractmethod
            def insert(self, index, value):
        ...
        ```
        - MutableSequence ê°€ Sequence ë¥¼ ìƒì† ë°›ìŒì„ í™•ì¸í•  ìˆ˜ ìˆìŒ
        - ì¶”ê°€ì ì¸ ìˆ˜ì • ë©”ì„œë“œë„ êµ¬í˜„ë˜ì–´ ìˆìŒ
        - Full Code ëŠ” `Example Codes` ì°¸ê³      
- ë‚´ì¥ëœ êµ¬ìƒ ì‹œí€€ìŠ¤í˜•ì´ ì‹¤ì œë¡œ Sequence ë‚˜ MutableSequence ì¶”ìƒë² ì´ìŠ¤ í´ë˜ìŠ¤ë¥¼ ìƒì†ë°›ì§€ëŠ” ì•Šì§€ë§Œ, ì´ ë‘ ì¶”ìƒ ë² ì´ìŠ¤ í´ë˜ìŠ¤ì˜ ê°€ìƒ ì„œë¸Œí´ë˜ìŠ¤ì´ë‹¤
    - list, tuple ë“±ì´ Sequence ì™€ MutableSequenceë¥¼ ìƒì†ë°›ì§€ ì•ŠìŒ
    - abc ëª¨ë“ˆì—ì„œ register í•˜ì—¬ ê°€ìƒì„œë¸Œí´ë˜ìŠ¤í™” í•´ ë†“ìŒ
        ```python
        MutableSequence.register(list)
        MutableSequence.register(bytearray)
        ```
        - Full Code ëŠ” `Example Codes` ì°¸ê³  
- Example Codes
    - [abc_of_sequence.py](./codes/02ì£¼ì°¨_chapter2-1_abc_of_sequence.py)

> ğŸ”¥ **ê°ì²´ì— ëŒ€í•œ ì°¸ì¡°ë¥¼ ë‹´ëŠ”ë‹¤(ë„˜ê¸´ë‹¤)** ì— ëŒ€í•˜ì—¬... 
>- ğŸ”¥ PyObject Structure Of CPython
>   - íŒŒì´ì¬ì—ì„œ ëª¨ë“  ê°ì²´ëŠ” **C êµ¬ì¡°ì²´(PyObject)** ê¸°ë°˜
>   - PyObject ê¸°ë³¸ êµ¬ì¡°
>       ```C
>       typedef struct _object {
>           Py_ssize_t ob_refcnt;   
>           PyTypeObject *ob_type;  
>       } PyObject;
>       ```
>       - ob_refcnt: ê°ì²´ê°€ ëª‡ ë²ˆ ì°¸ì¡°ë˜ê³  ìˆëŠ”ì§€ ë‚˜íƒ€ëƒ„ â†’ GCì—ì„œ ì‚¬ìš©ë¨
>       - ob_type: ì´ ê°ì²´ê°€ ë¬´ìŠ¨ íƒ€ì…ì¸ì§€ ê°€ë¦¬í‚¤ëŠ” í¬ì¸í„° (int, list, MyClass ë“±)
>   - ğŸ“Œ PyObjectëŠ” ëª¨ë“  ê°ì²´ì˜ ê³µí†µ ê¸°ë°˜(Base Struct) ì´ê³ , ê° íƒ€ì…ë³„ë¡œ ì—¬ê¸°ì— ìì‹ ë§Œì˜ êµ¬ì¡°ì²´ê°€ ì¶”ê°€ë¨
>   - PyFloatObject (float íƒ€ì… ê°ì²´)
>       ```C
>       // ì–œ macro ì„, ëª¨ë“  êµ¬ì¡°ì²´ì—ì„œ ì‚¬ìš©ë  í•„ë“œë¥¼ ë¯¸ë¦¬ ì •ì˜í•´ë‘ê³  ë³µë¶™í•´ ì“°ëŠ” ê²ƒ  
>       #define PyObject_HEAD  \
>       Py_ssize_t ob_refcnt; \
>       PyTypeObject *ob_type;  
>       // PyFloatObject 
>       typedef struct {
>           PyObject_HEAD       
>           double ob_fval;     // floatí˜• ì‹¤ì œ ê°’
>       } PyFloatObject;
>       ```
>       - **PyFloatObjectëŠ” PyObjectë¥¼ í™•ì¥í•œ êµ¬ì¡°ì²´**, ì‹¤ì œ float ê°’ì€ ob_fval ì— ì €ì¥ë¨
>   - ì˜ˆì‹œ!) pythonì—ì„œ a=1.1 (float) ë³€ìˆ˜ë¥¼ ì„ ì–¸í•˜ë©´...
>       ```C
>       PyObject *
>       PyFloat_FromDouble(double fval)
>       {
>           PyFloatObject *op = _Py_FREELIST_POP(PyFloatObject, floats);
>           if (op == NULL) {
>               op = PyObject_Malloc(sizeof(PyFloatObject));
>               if (!op) {
>                   return PyErr_NoMemory();
>               }
>               _PyObject_Init((PyObject*)op, &PyFloat_Type);
>           }
>           op->ob_fval = fval;
>           return (PyObject *) op;     // PyObject * íƒ€ì…ìœ¼ë¡œ ì—…ìºìŠ¤íŒ… í•´ì¤Œ - ëª¨ë“  ê°ì²´ë¥¼ ë²”ìš©ì ìœ¼ë¡œ ì²˜ë¦¬í•˜ê¸° ìœ„í•¨(Polymorphism)
>       }
>       PyObject *x = PyFloat_FromDouble(1.1);   // PyFloatObject ì˜ í¬ì¸í„° ì €ì¥(PyObject * íƒ€ì…ìœ¼ë¡œ)
>       ```
>	    - í™ì— PyFloatObject êµ¬ì¡°ì²´ ìƒì„±ë¨
>	    - ê·¸ ì£¼ì†Œë¥¼ PyObject*ë¡œ ì—…ìºìŠ¤íŒ…í•´ì„œ ë°˜í™˜
>	    - íŒŒì´ì¬ ë³€ìˆ˜ aëŠ” ì´ í¬ì¸í„°ë¥¼ ì°¸ì¡°í•˜ê²Œ ë¨
>- ğŸ”¥ ê²°ë¡  : í•¨ìˆ˜ í˜¸ì¶œ ì‹œ â€œê°ì²´ ì°¸ì¡°ë¥¼ ê°’ìœ¼ë¡œ ì „ë‹¬â€í•œë‹¤ëŠ” ê±´, ê²°êµ­ **ê°ì²´ì˜ ì£¼ì†Œ(í¬ì¸í„°)ë¥¼ ë³µì‚¬í•´ ë„˜ê¸°ëŠ” ê²ƒ**
>   - "ê°ì²´ ì°¸ì¡°"ëŠ” C ë ˆë²¨ì—ì„œ PyObject* ë¡œ í‘œí˜„ë˜ë©°, ê°ì²´ êµ¬ì¡°ì²´ì— ëŒ€í•œ **í¬ì¸í„°**
>   - ë‹¨, íŒŒì´ì¬ì€ ë©”ëª¨ë¦¬ ì•ˆì „ì„±, ì¶”ìƒí™”, **ê°€ë¹„ì§€ ì»¬ë ‰ì…˜(GC)**ì„ ìœ„í•´
>	    - ë©”ëª¨ë¦¬ ì§ì ‘ ì ‘ê·¼ ê¸ˆì§€
>	    - í¬ì¸í„° ì—°ì‚° ê¸ˆì§€
>	    - ê°ì²´ì˜ ìƒì„±/ì‚­ì œ/ê´€ë¦¬ ëª¨ë‘ ì¸í„°í”„ë¦¬í„°ì— ìœ„ì„
>   - ê·¸ë˜ì„œ í¬ì¸í„°ëŠ” ì¡´ì¬í•˜ì§€ë§Œ, **â€œì ‘ê·¼í•  ê¶Œí•œì€ ì—†ìŒâ€**
>   - ì¦‰, íŒŒì´ì¬ì€ í¬ì¸í„°ë¥¼ ì•ˆì „í•˜ê²Œ ê°ì‹¼ "ì°¸ì¡°" ê°œë…ë§Œ ë…¸ì¶œí•˜ë©°, í•¨ìˆ˜ í˜¸ì¶œ ì‹œ ì´ í¬ì¸í„°ê°€ **ê°’ì²˜ëŸ¼ ë³µì‚¬ë˜ì–´** ì „ë‹¬ë˜ëŠ” ê²ƒ

> ğŸ”¥ Call By Reference? Call By Value? 
>- ğŸ”¥ **Call By Object-Reference(Assignment)**
>   - íŒŒì´ì¬ì˜ ë³€ìˆ˜í• ë‹¹ì€ í•´ë‹¹ ê°ì²´ì— ëŒ€í•œ binding = ì°¸ì¡°ë¥¼ ì €ì¥í•œë‹¤(**Pointerê°™ì€ ì£¼ì†Œ ê°œë…**)
>       ```python
>       def modify(n):
>           n += 1
>       x = 1.1
>       y=x
>       z=x
>       print(modify(z))    # 2.1
>       print(x)    # 1.1
>       print(z)    # 1.1
>       ```
>       - 1.1ì€ ë©”ëª¨ë¦¬ì— í•˜ë‚˜ì˜ PyFloatObjectë¡œ ì¡´ì¬ / x, y, zëŠ” í•´ë‹¹ ê°ì²´ì˜ **ì£¼ì†Œ**ë¥¼ ì €ì¥
>       - ob_refcnt = 3 ì´ ë˜ê² ì§€ (ì´ ê°’ì´ **GC** ì— í™œìš©ë¨ - ì°¸ì¡° ì¹´ìš´íŒ… ê¸°ë°˜ ë©”ëª¨ë¦¬ ê´€ë¦¬)
>       - modify(z) ì´ ì‹¤í–‰ë˜ëŠ” ìˆœê°„, 1.1 ê°ì²´ì˜ ì°¸ì¡°íšŒìˆ˜ëŠ” 4ë¡œ ì ì‹œ ëŠ˜ì–´ë‚˜ë‚˜(n+=1 ì—°ì‚°ì‹œ ë‹¤ì‹œ 3ë¨),<br> **immutable ê°ì²´ì´ë¯€ë¡œ,** in-place ê°€ ì•„ë‹Œ **ìƒˆ ê°ì²´ ìƒì„± + ì°¸ì¡° ë°”ê¿”ì¹˜ê¸°**
>       - 2.1 ì€ ìƒˆë¡œìš´ PyFloatObject ë¡œ ì¡´ì¬í•˜ê²Œ ë˜ê³ , n ì´ í•´ë‹¹ ê°ì²´ ì£¼ì†Œë¥¼ ì°¸ì¡°í•¨(í•¨ìˆ˜ ì¢…ë£Œì‹œì—” ì‚¬ë¼ì§€ê² ì§€ -> GC ëŒ€ìƒ) 
>       - x, y, z ê°€ ê°€ë¥´í‚¤ë˜ 1.1 ê°ì²´ëŠ” ê·¸ëŒ€ë¡œ ì¡´ì¬
>       - ë§Œì•½ x, y, z ê°€ ë¦¬ìŠ¤íŠ¸ ê°ì²´ë¥¼ ê°€ë¥´í‚¤ê³ , í•¨ìˆ˜ ë‚´ì—ì„œ ë¦¬ìŠ¤íŠ¸ ê°ì²´ ìì²´ë¥¼ ë°”ê¿¨ë‹¤ë©´, ì›ë³¸ì— ì˜í–¥ì„ ì¤¬ê² ì§€(mutable ê°ì²´ íŠ¹ì„±)
>- ğŸ”¥ ê²°ë¡  : 
>   - ê°ì²´ ì°¸ì¡°(ì£¼ì†Œ)ë¥¼ ë„˜ê¸´ë‹¤
>   - íŒŒì´ì¬ì€, ê·¸ ì£¼ì†Œ ìì²´ë¥¼ ì§ì ‘ ì¡°ì‘í•  ìˆ˜ëŠ” ì—†ì–´ì„œ ê·¸ ì£¼ì†Œê°€ ê°€ë¦¬í‚¤ëŠ” ê°ì²´ì˜ ê°’ì„ ì¡°ì‘í•  ìˆ˜ ë°–ì— ì—†ë‹¤.
>   - ê·¸ ê°ì²´ê°€ mutableì´ë©´ ì›ë³¸ ê°’ì´ ë°”ë€Œê³ ,<br>ğŸ‘‰ Call by Reference ì²˜ëŸ¼ ë³´ì´ê² ì§€
>   - ê°ì²´ê°€ immutableì´ë©´ ìƒˆë¡œìš´ ê°ì²´ë¥¼ ë§Œë“¤ì–´ ìƒˆ ì°¸ì¡°ë¡œ ë°”ê¿”ì¹˜ëŠ” ê²ƒ<br>ğŸ‘‰ Call by Value ì²˜ëŸ¼ ë³´ì´ê² ì§€

## 2. List Comprehension & Generator Expression
### List Comprehension(listcomp) 
- sequence í˜¹ì€ ê¸°íƒ€ iterable ê°ì²´ë¡œë¶€í„° ìƒˆ ë¦¬ìŠ¤íŠ¸ ê°ì²´ë¥¼ ë§Œë“¤ê¸° ìœ„í•¨
- **Eager Evaluation**
    ```python
        words = '$#@asdq'
        codes = [ord(word) for word in words]
    ```
- ë‹¨, ìƒì„±í•œ ë¦¬ìŠ¤íŠ¸ë¥¼ ì‚¬ìš©í•  ê²ƒì´ ì•„ë‹ˆë¼ë©´(ex.í•œ ë²ˆë§Œ ìˆœíšŒí•˜ë©´ ë  ê²½ìš°), ì•ˆì“°ëŠ” ê²ƒì´ ì¢‹ìŒ
    ```python
        t = tuple([x**2 for x in range(10)])
    ```
    - tuple ì„ ë§Œë“¤ê¸°ìœ„í•´ ë¦¬ìŠ¤íŠ¸ë¥¼ ìƒì„±í•  í•„ìš”ê°€ ì—†ìŒ.(í•œ ë²ˆ ìˆœíšŒí•˜ê³  ë²„ë¦´ê±°ë‹ˆê¹Œ)
    - ë¦¬ìŠ¤íŠ¸ê°€ ë‹¤ ë©”ëª¨ë¦¬ì— ì˜¬ë¼ê°€ëŠ” ë¹„íš¨ìœ¨ì´ ìƒê¹€
    - genexp ê°€ íš¨ìœ¨ì (Lazy Evaluation) 

- map()/filter()/lambda expr ì¡°í•©ë³´ë‹¤ list comp ê°€ ë¹ ë¥´ê³  ì§ê´€ì 
    - list comprehensionì€ Cë¡œ êµ¬í˜„ëœ ë‚´ë¶€ ë£¨í”„ë¥¼ ì‚¬ìš©í•˜ì—¬, íŒŒì´ì¬ ì¸í„°í”„ë¦¬í„° ë ˆë²¨ì˜ í•¨ìˆ˜ í˜¸ì¶œ ì˜¤ë²„í—¤ë“œê°€ ì—†ìŒ. (íŒŒì´ì¬ì—ì„  í•¨ìˆ˜ í˜¸ì¶œ ì˜¤ë²„í—¤ë“œê°€ í° ë¹„ìš©ì„ ì°¨ì§€í•¨)
    - dis.dis í™œìš© ë¹„êµ : íŒŒì´ì¬ ì¸í„°í”„ë¦¬í„°ê°€ ë‚´ë¶€ì ìœ¼ë¡œ ì–´ë–¤ ëª…ë ¹ì–´(opcode)ë¥¼ ì‹¤í–‰í•˜ëŠ”ì§€ ì•Œ ìˆ˜ ìˆìŒ
        ```python
        import dis
        dis.dis('[x**2 for x in range(10) if x % 2 == 0]')
        """
        1           0 LOAD_CONST               0 (<code object <listcomp> at 0x1026469d0, file "<dis>", line 1>)
                    2 LOAD_CONST               1 ('<listcomp>')
                    4 MAKE_FUNCTION            0
                    6 LOAD_NAME                0 (range)
                    8 LOAD_CONST               2 (10)
                    10 CALL_FUNCTION            1
                    12 GET_ITER
                    14 CALL_FUNCTION            1
                    16 RETURN_VALUE
        Disassembly of <code object <listcomp> at 0x1026469d0, file "<dis>", line 1>:
        1           0 BUILD_LIST               0
                    2 LOAD_FAST                0 (.0)
                >>    4 FOR_ITER                24 (to 30)
                    6 STORE_FAST               1 (x)
                    8 LOAD_FAST                1 (x)
                    10 LOAD_CONST               0 (2)
                    12 BINARY_MODULO
                    14 LOAD_CONST               1 (0)
                    16 COMPARE_OP               2 (==)
                    18 POP_JUMP_IF_FALSE        4
                    20 LOAD_FAST                1 (x)
                    22 LOAD_CONST               0 (2)
                    24 BINARY_POWER
                    26 LIST_APPEND              2
                    28 JUMP_ABSOLUTE            4
                >>   30 RETURN_VALUE
        """ 
        ```
        - FOR_ITER, BINARY_MODULO, COMPARE_OP, BINARY_POWER ì™€ ê°™ì€ ê°„ë‹¨í•œ ì—°ì‚° opcode ìœ„ì£¼
	    - í•¨ìˆ˜ í˜¸ì¶œ ì—†ì´ ë£¨í”„ë¥¼ ì§ì ‘ ìˆœíšŒí•¨ â†’ ë¹ ë¦„! 
        ```python
        dis.dis('list(map(lambda x: x**2, filter(lambda x: x % 2 == 0, range(10))))')
        """
        1           0 LOAD_NAME                0 (list)
                    2 LOAD_NAME                1 (map)
                    4 LOAD_CONST               0 (<code object <lambda> at 0x104a4ea80, file "<dis>", line 1>)
                    6 LOAD_CONST               1 ('<lambda>')
                    8 MAKE_FUNCTION            0
                    10 LOAD_NAME                2 (filter)
                    12 LOAD_CONST               2 (<code object <lambda> at 0x104a4eb30, file "<dis>", line 1>)
                    14 LOAD_CONST               1 ('<lambda>')
                    16 MAKE_FUNCTION            0
                    18 LOAD_NAME                3 (range)
                    20 LOAD_CONST               3 (10)
                    22 CALL_FUNCTION            1
                    24 CALL_FUNCTION            2
                    26 CALL_FUNCTION            2
                    28 CALL_FUNCTION            1
                    30 RETURN_VALUE

        Disassembly of <code object <lambda> at 0x104a4ea80, file "<dis>", line 1>:
        1           0 LOAD_FAST                0 (x)
                    2 LOAD_CONST               1 (2)
                    4 BINARY_POWER
                    6 RETURN_VALUE

        Disassembly of <code object <lambda> at 0x104a4eb30, file "<dis>", line 1>:
        1           0 LOAD_FAST                0 (x)
                    2 LOAD_CONST               1 (2)
                    4 BINARY_MODULO
                    6 LOAD_CONST               2 (0)
                    8 COMPARE_OP               2 (==)
                    10 RETURN_VALUE
        """
        ```
        - MAKE_FUNCTION, CALL_FUNCTIONì´ ë°˜ë³µ ì‹¤í–‰(lambda í•¨ìˆ˜ ê³„ì† í˜¸ì¶œ) â†’ í•¨ìˆ˜ í˜¸ì¶œ ì˜¤ë²„í—¤ë“œ ì¦ê°€
	    - range(10) â†’ filter â†’ map â†’ list() ìˆœìœ¼ë¡œ ì¤‘ì²© í˜¸ì¶œ
    - ì†ë„ ë¹„êµ ì˜ˆì‹œ
        - [check_speed_of_listcomp.py](./codes/02ì£¼ì°¨_chapter2-2_check_speed_of_listcomp.py)

### Generator Expression(genexp)
- ìƒì„±ìì— ì „ë‹¬í•  ë°ì´í„°ë¥¼ í†µì§¸ë¡œ ë§Œë“¤ì§€ ì•Šê³ , iterator protocolì„ ì´ìš©í•˜ì—¬, í•„ìš”í• ë•Œ í•˜ë‚˜ì”© ìƒì„±í•¨.
- **Lazy Evaluation**
    ```python
    squares = (x**2 for x in range(10))
    print(squares)  # <generator object <genexpr> at 0x100523510>
    print(next(squares))    # 0
    print(next(squares))    # 1
    print(next(squares))    # 4
    print(next(squares))    # 9
    ```
- example of **Cartesian Product**
    ```python
    colors = ['black','green','yellow']
    sizes = ['S','M','L','XL']
    for cloth in (f"{c}_{s}" for c in colors for s in sizes):
        print(cloth)
    """output
    black_S
    black_M
    black_L
    black_XL
    green_S
    green_M
    green_L
    green_XL
    yellow_S
    yellow_M
    yellow_L
    yellow_XL
    """
    ```


## 3. Tuple as a record or immutable list
- As a Record
    ```python
    traveler_ids = [('USA','1234123'),('BRA','8174816'),('KOR','1898519490'),('ESP','98171535748')]
    for passport in traveler_ids :
        print('%s/%s' % passport)
    
    for country, _ in traveler_ids :
        print(country)
    ```
    - for ë£¨í”„ ëŒ ë•Œ, passport ë³€ìˆ˜ê°€ ë¦¬ìŠ¤íŠ¸ ë‚´ ê° íŠœí”Œê°ì²´ì— binding
    - for ë£¨í”„ëŠ” íŠœí”Œì˜ ê° ìš”ì†Œë¥¼ ê°€ì ¸ì˜¤ëŠ” ë°©ë²•ì„ ì• -> **Unpacking**
    - ê´€ì‹¬ ì—†ëŠ” ìš”ì†ŒëŠ” ë”ë¯¸ë³€ìˆ˜ë¥¼ ë‚˜íƒ€ë‚´ëŠ” _ ì£¼ë¡œ ì‚¬ìš©í•¨ 
        - ìœ„ì˜ ê²½ìš° ì–¸ë”ë°”ë„ binding ë¨.  match/case ë¬¸ ì—ì„  binding ì•ˆ ë¨.

- As a Immutable List
    - list ë³´ë‹¤ ë©”ëª¨ë¦¬ë¥¼ ì ê²Œ ì†Œë¹„í•˜ëŠ” tuple 
        - ê¸¸ì´ê°€ ê³ ì •ë˜ì–´ ìˆìœ¼ë‹ˆ í•„ìš”í•œ ë§Œí¼ë§Œ ë©”ëª¨ë¦¬ í• ë‹¹. list ëŠ” ì¶”ê°€í•  ê²ƒ ìƒê°í•´ ì¢€ ë” í• ë‹¹í•¨.
        - tuple ìš”ì†Œì— ëŒ€í•œ ì°¸ì¡°ëŠ” tuple êµ¬ì¡°ì²´ì— ë°°ì—´ë¡œ ì €ì¥ë¨. list ëŠ” ë‹¤ë¥¸ ê³³ì— ì €ì¥ëœ ì°¸ì¡° ë°°ì—´ì— ëŒ€í•œ í¬ì¸í„°ë¥¼ ê°€ì§ <br>-> ìš”ì†Œê°€ ëŠ˜ì–´ë‚˜ë©´, ê³µê°„ì„ ìƒˆë¡œ í™•ë³´í•˜ê³  ì°¸ì¡° ë°°ì—´ ì¬í• ë‹¹ í•„ìš”í•˜ë¯€ë¡œ<br>-> CPU Cache íš¨ìœ¨ ê°ì†Œ


## 4. Sequence unpacking & pattern-matching
- Sequence Unpacking
    - ê¸°ë³¸ unpacking
    ```python
    import os
    path = '/Users/jeongmo/local-git-repo/study-fluent-python-2e/ë°°ì •ëª¨/sync-with-upstream.sh'
    _, filename = os.path.split(path)   # (path, last_part) tuple ìƒì„± & unpacking
    print(filename) # sync-with-upstream.sh
    ```
    - í™•ì¥ unpacking
    ```python
    a, *b = [1, 2, 3, 4]
    print(a, b)  # 1, [2, 3, 4]
    a, *b, c = [1, 2, 3, 4, 5]
    print(a, b, c)  # 1 [2, 3, 4] 5
    ```
    - enumerate, zip ê°™ì€ iterable ê°ì²´ë„ ì „ë¶€ unpacking ê°€ëŠ¥í•˜ë‹¤
    ```python
    la = ['A', 'B', 'C']
    lb = [1, 2, 3]
    lc = [9, 8, 7]
    for a, b, c in zip(la, lb, lc):
        print(a, b, c)
    ```
- Sequence Pattern Matching(py 3.10~)
    ```python
    def test(seq):
    match seq:
        case [1, 2, 3]:
            return "ì •í™•íˆ [1, 2, 3]ê³¼ ì¼ì¹˜!"
        case [1, 2, _]:
            return "ì„¸ ë²ˆì§¸ ê°’ì€ ë¬´ì‹œí•˜ê³  [1, 2, _] íŒ¨í„´ê³¼ ì¼ì¹˜!"
        case [1, *rest]:
            return f"1ë¡œ ì‹œì‘í•˜ê³  ë‚˜ë¨¸ì§€ëŠ” {rest}!"
        case _:
            return "ì–´ë–¤ íŒ¨í„´ì—ë„ ì•ˆ ë§ìŒ"
    ```
    - ì–¸íŒ¨í‚¹ + ì™€ì¼ë“œì¹´ë“œ ì¡°í•©
    ```python
    def test(seq):
    match seq:
        case [_, second, *_]:
            return f"ë‘ ë²ˆì§¸ ê°’ì€ {second}"
    ```
## 5. Slicing    
- ìŠ¬ë¼ì´ìŠ¤ ê°ì²´ : slice(start, stop, step) - ì„œë¸Œë¦¬ìŠ¤íŠ¸ë¥¼ ë§Œë“¤ê¸° ìœ„í•œ ì¸ë±ìŠ¤ ì •ë³´(start, stop, step)ë¥¼ ë‹´ê³  ìˆëŠ” ê°ì²´
- ë™ì‘ ë°©ì‹ 
    ```python
    lst[1:4]
    # slice(1, 4)
    # print(s.start, s.stop, s.step)  -> 1 4 None
    ```
    - slice(1, 4) ê°ì²´ìƒì„±
	- lst.\_\_getitem\_\_(slice(1, 4)) í˜¸ì¶œ
    - **ì¦‰, ìŠ¬ë¼ì´ì‹±ì€ ì‹¤ì œë¡œëŠ” ì¸ë±ìŠ¤ ì ‘ê·¼ì´ ì•„ë‹ˆë¼ slice ê°ì²´ë¥¼ ì¸ìë¡œ ë„˜ê¸°ëŠ” í•¨ìˆ˜ í˜¸ì¶œ!**
- íŒŒì´ì¬ ë¦¬ìŠ¤íŠ¸ëŠ” ìŠ¬ë¼ì´ìŠ¤ í• ë‹¹ ì‹œ iterableë§Œ í—ˆìš©í•˜ë„ë¡ êµ¬í˜„ë˜ì–´ ìˆìŒ 
    ```python
    l = list(range(10)) # [0,1,2,3,4,5,6,7,8,9]
    l[2:5] = [100] # [0,1,100,5,6,7,8,9]
    l[2:5] = 100 # TypeError : can only assign iterable
    ```
    - ì™œê·¸ëŸ´ê¹Œ? : slicing ì€ ê²°êµ­ slice ê°ì²´ë¥¼ \_\_getitem\_\_ ë©”ì„œë“œ \_\_setitem\_\_ ë©”ì„œë“œ ì¸ìë¡œ ë„˜ê¸°ëŠ”ê²ƒ.. ì•„ë˜ë¥¼ ë³´ë©´ ì™œ iterable ì´ì–´ì•¼ í•˜ëŠ”ì§€ ì´í•´ê°€ ê°ˆê²ƒì„...
    - iterable ì´ ì•„ë‹Œ ê·¸ëƒ¥ ê°’ìœ¼ë¡œ ì“°ê³ ì‹¶ë‹¤ë©´, indexing ì„ í•´ì•¼ê² ì§€... 
- \_\_getitem\_\_ , \_\_setitem\_\_ ì§ì ‘ êµ¬í˜„í•´ë³´ì(ì™œ iterable ê°ì²´ë§Œ í• ë‹¹ê°€ëŠ¥í•œì§€ ì•Œê²Œë ê±°ì•¼)
    ```python
    class MyList:
        def __init__(self,data):
            self.data = data # [10, 20, 30, 40, 50] ë¦¬ìŠ¤íŠ¸ ë°›ëŠ”ë‹¤ ê°€ì •. ë‹¨, êµ¬í˜„ì€ ì§ì ‘
    
        def __getitem__(self, index):
            if isinstance(index, slice):
                indices = range(*index.indices(len(self.data)))
                return [self.data[i] for i in indices]   #ì´ëŸ° ë°©ì‹ìœ¼ë¡œ ë„ëŠ”ê±°
            elif isinstance(index, int):
                return self.data[index]
            else:
                raise TypeError
    
        def __setitem__(self, index, value):
            if isinstance(index, slice):
                indices = list(range(*index.indices(len(self.data))))
                for i in reversed(indices):
                    del self.data[i]
                insert_at = indices[0] if indices else len(self.data)
                for offset, v in enumerate(value):     # ì™œ slice ê°ì²´ë¥¼ í†µí•œ í• ë‹¹ì´ iterable ê°ì²´ë§Œ ê°€ëŠ¥í•œì§€ ì•Œ ìˆ˜ ìˆì§€
                    self.data.insert(insert_at + offset, v)
            elif isinstance(index, int):
                self.data[index] = value
            else:
                raise TypeError
    ```


